wordle_api/__init__.py
wordle_api/api.py
wordle_api/constants.py
wordle_api/exceptions.py
wordle_api/wordle.py
wordle_api/words.py
wordle_api-1.1.2.dist-info/LICENSE.md
wordle_api-1.1.2.dist-info/WHEEL
wordle_api-1.1.2.dist-info/METADATA
wordle_api-1.1.2.dist-info/RECORD
